air_waiter/__init__.py
air_waiter/py.typed
air_waiter/wait.py
air_waiter-1.3.0.dist-info/METADATA
air_waiter-1.3.0.dist-info/WHEEL
air_waiter-1.3.0.dist-info/licenses/LICENSE
air_waiter-1.3.0.dist-info/RECORD
