Metadata-Version: 2.4
Name: air-waiter
Version: 1.3.0
Summary: Waiter
Project-URL: Source, https://github.com/airreality/air-waiter
Author-email: Anton Ryazantsev <airunreality@gmail.com>
Maintainer-email: Anton Ryazantsev <airunreality@gmail.com>
License: MIT License
License-File: LICENSE
Requires-Python: >=3.12
